README.md
setup.py
tests/__init__.py
tests/test_board.py
v13r93w1nn7/__init__.py
v13r93w1nn7/board.py
v13r93w1nn7/game.py
v13r93w1nn7.egg-info/PKG-INFO
v13r93w1nn7.egg-info/SOURCES.txt
v13r93w1nn7.egg-info/dependency_links.txt
v13r93w1nn7.egg-info/top_level.txt