Metadata-Version: 2.1
Name: v13r93w1nn7
Version: 0.0.6
Summary: extended version of the board game «Vier gewinnt»
Home-page: https://github.com/patrickbucher/v13r93w1nn7
Author: Patrick Bucher
Author-email: patrick.bucher@mailbox.org
License: UNKNOWN
Platform: UNKNOWN
Classifier: Programming Language :: Python :: 3
Classifier: License :: OSI Approved :: GNU General Public License v3 (GPLv3)
Classifier: Operating System :: OS Independent
Requires-Python: >=3.8
